RTL/fifo.v
//////////////////////////////////////////////////////////////////////////////////
// Institution: Ecole de mines de Saint-Etienne
// Engineer: Diego Alejandro Maldonado Marin
// 
// Create Date: 22.04.2026
// Design Name: symetric fifo
// Module Name: fifo
// Project Name: 
// Target Devices: 
// Tool Versions: 
// Description: Esta memoria esta pensada para que la profundidad sea potencia de 2,
// de esta manera no es necesario comparar los punteros para saber cuando reiniciar.
//
// Revision:
// Revision 0.01 - File Created
// Additional Comments:
// 
//////////////////////////////////////////////////////////////////////////////////

module fifo #(
    parameter WIDTH = 8,
    parameter DEPTH = 8
)(
    // Inputs
    input wire clk,
    input wire rst,
    input wire wr_en,
    input wire rd_en,
    input wire [WIDTH-1:0] d_in,
    // Outputs
    output wire [WIDTH-1:0] d_out,
    output reg full,
    output reg empty
);

parameter AW = $clog2(DEPTH);

reg [DEPTH-1:0][WIDTH-1:0] MEM;

reg [AW:0] wr_ptr_q, wr_ptr_n;
reg [AW:0] rd_ptr_q, rd_ptr_n;

reg [WIDTH-1:0] d_out_q, d_out_n;

// DFF - d_out 
always @(posedge clk or posedge rst) begin
    if (rst) begin
        d_out_q <= 0;
    end else begin
        d_out_q <= d_out_n;
    end
end

// DFF - MEM 
always @(posedge clk or posedge rst) begin
    if (rst) begin
        MEM <= 0;
    end else if(wr_en && !full && !(rd_en && empty)) begin
        MEM[wr_ptr_q[AW-1:0]] = d_in;
    end
end

// DFF - wr_ptr and rd_ptr
always @(posedge clk or posedge rst) begin
    if (rst) begin
        wr_ptr_q <= 0;
        rd_ptr_q <= 0;
    end else begin
        wr_ptr_q <= wr_ptr_n;
        rd_ptr_q <= rd_ptr_n;
    end
end

always @(*) begin
    // Write
    if(wr_en && !full && !(rd_en && empty)) begin
        wr_ptr_n = wr_ptr_q + 1'b1;
    end 
    else begin
        wr_ptr_n = wr_ptr_q;
    end

    // Read
    if(rd_en && !empty) begin
        rd_ptr_n = rd_ptr_q + 1'b1;
    end 
    else begin
        rd_ptr_n = rd_ptr_q;
    end

    // Output
    if (rd_en && wr_en && empty) begin
        d_out_n = d_in;
    end
    else if(rd_en && !empty) begin
        d_out_n = MEM[rd_ptr_q[AW-1:0]];
    end 
    else begin
        d_out_n = d_out_q;
    end
end

always @(*) begin
    full = ((wr_ptr_q[AW-1:0]==rd_ptr_q[AW-1:0]) && (wr_ptr_q[AW]!=rd_ptr_q[AW]));
    empty = wr_ptr_q == rd_ptr_q;
end

assign d_out = d_out_q;

endmodule

RTL/fifo_TB.v
`timescale 1ns / 1ps

module tb_fifo();

    parameter WIDTH = 8;
    parameter DEPTH = 8;

    reg clk;
    reg rst;
    reg wr_en;
    reg rd_en;
    reg [WIDTH-1:0] d_in;

    wire [WIDTH-1:0] d_out;
    wire full;
    wire empty;

    integer idx;


    fifo #(
        .WIDTH(WIDTH),
        .DEPTH(DEPTH)
    ) dut (
        .clk(clk),
        .rst(rst),
        .wr_en(wr_en),
        .rd_en(rd_en),
        .d_in(d_in),
        .d_out(d_out),
        .full(full),
        .empty(empty)
    );


    initial begin
        clk = 1;
        forever #5 clk = ~clk; // (Periodo de 10ns -> 100MHz)
    end


    initial begin
        // Configuración para generar archivos de forma de onda (VCD)
        $dumpfile("fifo_TB.vcd");
        $dumpvars(0, tb_fifo);
        for(idx = 0; idx < DEPTH; idx = idx +1)  $dumpvars(0, tb_fifo.dut.MEM[idx]);

        // 0. Inicialización de señales
        rst = 1;
        wr_en = 0;
        rd_en = 0;
        d_in = 0;

        // Esperar un par de ciclos y soltar el reset
        #20 rst = 0;
        #10;

        $display("--- Iniciando pruebas de la FIFO ---");

        // 1. Prueba de ESCRITURA hasta llenar la memoria
        $display("[%0t] TEST 1: Escribiendo datos en la FIFO...", $time);
        wr_en = 1;
        // Escribimos DEPTH veces para intentar llenarla
        repeat (DEPTH) begin
            d_in = $random; // Dato aleatorio
            #10;
        end
        wr_en = 0;
        #20;

        // 2. Prueba de LECTURA hasta vaciar la memoria
        $display("[%0t] TEST 2: Leyendo datos de la FIFO...", $time);
        rd_en = 1;
        repeat (DEPTH) begin
            #10;
        end
        rd_en = 0;
        #20;

  

        $display("[%0t] TEST 3: Escritura y Lectura simultánea...", $time);
        // Primero metemos un dato
        rd_en = 1; wr_en = 1; d_in = 8'hAA; #10;
        // Ahora leemos y escribimos al mismo tiempo
        rd_en = 1; wr_en = 1; d_in = 8'hBB; #10;
        rd_en = 1; wr_en = 1; d_in = 8'hCC; #10;
        
        // Dejamos de escribir, solo leemos el último
        wr_en = 0; #10;
        rd_en = 0; #20;

        $display("[%0t] --- Pruebas finalizadas ---", $time);
        $finish;
    end


    always @(posedge clk) begin
        if (wr_en && !full && !rst)
            $display("Write: d_in = %h | wr_ptr = %d", d_in, dut.wr_ptr_q);
        if (rd_en && !empty && !rst)
            $display("Read:   d_out = %h | rd_ptr = %d", dut.MEM[dut.rd_ptr_q], dut.rd_ptr_q);
    end

endmodule

RTL/fifo_TB.vcd
$date
	Thu Apr 30 10:02:52 2026
$end
$version
	Icarus Verilog
$end
$timescale
	1ps
$end
$scope module tb_fifo $end
$var wire 1 ! full $end
$var wire 1 " empty $end
$var wire 8 # d_out [7:0] $end
$var parameter 32 $ DEPTH $end
$var parameter 32 % WIDTH $end
$var reg 1 & clk $end
$var reg 8 ' d_in [7:0] $end
$var reg 1 ( rd_en $end
$var reg 1 ) rst $end
$var reg 1 * wr_en $end
$var integer 32 + idx [31:0] $end
$scope module dut $end
$var wire 1 & clk $end
$var wire 8 , d_in [7:0] $end
$var wire 8 - d_out [7:0] $end
$var wire 1 ( rd_en $end
$var wire 1 ) rst $end
$var wire 1 * wr_en $end
$var parameter 32 . DEPTH $end
$var parameter 32 / WIDTH $end
$var reg 8 0 d_out_n [7:0] $end
$var reg 8 1 d_out_q [7:0] $end
$var reg 1 " empty $end
$var reg 1 ! full $end
$var reg 3 2 rd_ptr_n [2:0] $end
$var reg 3 3 rd_ptr_q [2:0] $end
$var reg 3 4 wr_ptr_n [2:0] $end
$var reg 3 5 wr_ptr_q [2:0] $end
$upscope $end
$upscope $end
$scope module tb_fifo $end
$scope module dut $end
$var reg 8 6 \MEM[0] [7:0] $end
$upscope $end
$upscope $end
$scope module tb_fifo $end
$scope module dut $end
$var reg 8 7 \MEM[1] [7:0] $end
$upscope $end
$upscope $end
$scope module tb_fifo $end
$scope module dut $end
$var reg 8 8 \MEM[2] [7:0] $end
$upscope $end
$upscope $end
$scope module tb_fifo $end
$scope module dut $end
$var reg 8 9 \MEM[3] [7:0] $end
$upscope $end
$upscope $end
$scope module tb_fifo $end
$scope module dut $end
$var reg 8 : \MEM[4] [7:0] $end
$upscope $end
$upscope $end
$scope module tb_fifo $end
$scope module dut $end
$var reg 8 ; \MEM[5] [7:0] $end
$upscope $end
$upscope $end
$scope module tb_fifo $end
$scope module dut $end
$var reg 8 < \MEM[6] [7:0] $end
$upscope $end
$upscope $end
$scope module tb_fifo $end
$scope module dut $end
$var reg 8 = \MEM[7] [7:0] $end
$upscope $end
$upscope $end
$enddefinitions $end
$comment Show the parameter values. $end
$dumpall
b1000 /
b1000 .
b1000 %
b1000 $
$end
#0
$dumpvars
bx =
bx <
bx ;
bx :
bx 9
bx 8
bx 7
bx 6
b0 5
b0 4
b0 3
b0 2
b0 1
b0 0
b0 -
b0 ,
b1000 +
0*
1)
0(
b0 '
1&
b0 #
1"
0!
$end
#5000
0&
#10000
1&
#15000
0&
#20000
1&
0)
#25000
0&
#30000
0"
b1 5
b100100 6
b10 4
1&
b100100 '
b100100 ,
1*
#35000
0&
#40000
b11 4
b10 5
b10000001 7
1&
b10000001 '
b10000001 ,
#45000
0&
#50000
b100 4
b11 5
b1001 8
1&
b1001 '
b1001 ,
#55000
0&
#60000
b101 4
b100 5
b1100011 9
1&
b1100011 '
b1100011 ,
#65000
0&
#70000
b110 4
b101 5
b1101 :
1&
b1101 '
b1101 ,
#75000
0&
#80000
b111 4
b110 5
b10001101 ;
1&
b10001101 '
b10001101 ,
#85000
0&
#90000
1!
b111 4
b111 5
b1100101 <
1&
b1100101 '
b1100101 ,
#95000
0&
#100000
1&
b10010 '
b10010 ,
#105000
0&
#110000
1&
0*
#115000
0&
#120000
1&
#125000
0&
#130000
0!
b1 3
b100100 #
b100100 -
b100100 1
b10000001 0
b10 2
1&
1(
#135000
0&
#140000
b1001 0
b11 2
b10000001 #
b10000001 -
b10000001 1
b10 3
1&
#145000
0&
#150000
b1100011 0
b100 2
b11 3
b1001 #
b1001 -
b1001 1
1&
#155000
0&
#160000
b1101 0
b101 2
b1100011 #
b1100011 -
b1100011 1
b100 3
1&
#165000
0&
#170000
b10001101 0
b110 2
b101 3
b1101 #
b1101 -
b1101 1
1&
#175000
0&
#180000
b1100101 0
b111 2
b10001101 #
b10001101 -
b10001101 1
b110 3
1&
#185000
0&
#190000
1"
b1100101 0
b111 2
b111 3
b1100101 #
b1100101 -
b1100101 1
1&
#195000
0&
#200000
1&
#205000
0&
#210000
1&
0(
#215000
0&
#220000
1&
#225000
0&
#230000
b10101010 0
b0 2
0"
b0 5
b10101010 =
b1 4
1&
b10101010 '
b10101010 ,
1*
1(
#235000
0&
#240000
b10111011 0
b1 2
b10 4
b10101010 #
b10101010 -
b10101010 1
b0 3
b1 5
b10111011 6
1&
b10111011 '
b10111011 ,
#245000
0&
#250000
b11001100 0
b10 2
b11 4
b1 3
b10 5
b10111011 #
b10111011 -
b10111011 1
b11001100 7
1&
b11001100 '
b11001100 ,
#255000
0&
#260000
1"
b11001100 0
b10 2
b11001100 #
b11001100 -
b11001100 1
b10 3
b10 4
1&
0*
#265000
0&
#270000
1&
0(
