sync_fifo.sv
`timescale 1ns/1ps

module sync_fifo #(
    parameter DEPTH = 8,
    parameter WIDTH = 8
)(
    input logic clk,
    input logic rst_n,
    input logic wr_en_i,
    input logic [WIDTH-1:0] din_i,
    input logic rd_en_i,
    output logic [WIDTH-1:0] dout_o,
    output logic full_o,
    output logic empty_o
);

logic [WIDTH-1:0] mem [0:DEPTH-1];

localparam int nbit = 
    DEPTH <= 1 ? 1 :
    $clog2(DEPTH) - 1;
localparam int ncount = $clog2(DEPTH + 1) - 1;


logic [nbit:0] wrptr_q;
logic [nbit:0] rdptr_q;
logic [ncount:0] count_q;

logic [nbit:0] wrptr_d;
logic [nbit:0] rdptr_d;
logic [ncount:0] count_d;

assign empty_o = (count_q == 0);
assign full_o = (count_q == DEPTH);


always_comb begin
    wrptr_d = wrptr_q;
    rdptr_d = rdptr_q;
    count_d = count_q;

    if (wr_en_i && rd_en_i) begin
        if(!empty_o) begin
            if (wrptr_q == DEPTH-1)
                wrptr_d = '0;
            else
                wrptr_d = wrptr_q + 1;

            if (rdptr_q == DEPTH-1)
                rdptr_d = '0;
            else
                rdptr_d = rdptr_q + 1;
            count_d = count_q;
        end
    end
    else if (wr_en_i && !full_o) begin
        if (wrptr_q == DEPTH-1)
            wrptr_d = '0;
        else
            wrptr_d = wrptr_q + 1;
        count_d = count_q + 1;

    end
    else if (rd_en_i && !empty_o) begin
        if (rdptr_q == DEPTH-1)
            rdptr_d = '0;
        else
            rdptr_d = rdptr_q + 1;
        count_d = count_q - 1;
    end
end

always_ff @(posedge clk) begin
    if (!rst_n) begin
        wrptr_q <= '0;
        rdptr_q <= '0;
        count_q <= '0;
        dout_o <= '0;
    end
    else begin
        wrptr_q <= wrptr_d;
        rdptr_q <= rdptr_d;
        count_q <= count_d;
        if (wr_en_i && ((!rd_en_i && !full_o) || (rd_en_i && !empty_o))) begin
            mem[wrptr_q] <= din_i;
        end
        if (wr_en_i && rd_en_i && empty_o) begin
            dout_o <= din_i;
        end 
        else if (rd_en_i && !empty_o) begin
            dout_o <= mem[rdptr_q];
        end 
        else begin
            dout_o <= 0;
        end
    end
end


endmodule

sync_fifo_TB.sv
`timescale 1ns / 1ps

module tb_fifo();

    parameter WIDTH = 8;
    parameter DEPTH = 8;

    logic clk;
    logic rst_n;
    logic wr_en;
    logic rd_en;
    logic [WIDTH-1:0] d_in;

    logic [WIDTH-1:0] d_out;
    logic full;
    logic empty;

    integer idx;


    sync_fifo #(
        .WIDTH(WIDTH),
        .DEPTH(DEPTH)
    ) dut (
        .clk(clk),
        .rst_n(rst_n),
        .wr_en_i(wr_en),
        .rd_en_i(rd_en),
        .din_i(d_in),
        .dout_o(d_out),
        .full_o(full),
        .empty_o(empty)
    );


    initial begin
        clk = 1;
        forever #5 clk = ~clk; // (Periodo de 10ns -> 100MHz)
    end


    initial begin
        // Configuración para generar archivos de forma de onda (VCD)
        $dumpfile("fifo_TB.vcd");
        $dumpvars(0, tb_fifo);
        for(idx = 0; idx < DEPTH; idx = idx +1)  $dumpvars(0, tb_fifo.dut.mem[idx]);

        // 0. Inicialización de señales
        rst_n = 0;
        wr_en = 0;
        rd_en = 0;
        d_in = 0;

        // Esperar un par de ciclos y soltar el reset
        #20 rst_n = 1;
        #10;

        $display("--- Iniciando pruebas de la FIFO ---");

        // 1. Prueba de ESCRITURA hasta llenar la memoria
        $display("[%0t] TEST 1: Escribiendo datos en la FIFO...", $time);
        wr_en = 1;
        // Escribimos DEPTH veces para intentar llenarla
        repeat (DEPTH) begin
            d_in = $random; // Dato aleatorio
            #10;
        end
        wr_en = 0;
        #20;

        // 2. Prueba de LECTURA hasta vaciar la memoria
        $display("[%0t] TEST 2: Leyendo datos de la FIFO...", $time);
        rd_en = 1;
        repeat (DEPTH+3) begin
            #10;
        end
        rd_en = 0;
        #20;

  

        $display("[%0t] TEST 3: Escritura y Lectura simultánea...", $time);
        // Primero metemos un dato
        rd_en = 1; wr_en = 1; d_in = 8'hAA; #10;
        // Ahora leemos y escribimos al mismo tiempo
        rd_en = 1; wr_en = 1; d_in = 8'hBB; #10;
        rd_en = 1; wr_en = 1; d_in = 8'hCC; #10;
        
        // Dejamos de escribir, solo leemos el último
        wr_en = 0; #10;
        rd_en = 0; #20;

        $display("[%0t] --- Pruebas finalizadas ---", $time);
        $finish;
    end


    always @(posedge clk) begin
        if (wr_en && !full && !rst_n)
            $display("Write: d_in = %h | wr_ptr = %d", d_in, dut.wrptr_q);
        if (rd_en && !empty && !rst_n)
            $display("Read:   d_out = %h | rd_ptr = %d", dut.mem[dut.rdptr_q], dut.rdptr_q);
    end

endmodule

fifo_TB.vcd
$date
	Thu Apr 30 12:20:54 2026
$end
$version
	Icarus Verilog
$end
$timescale
	1ps
$end
$scope module tb_fifo $end
$var wire 1 ! full $end
$var wire 1 " empty $end
$var wire 8 # d_out [7:0] $end
$var parameter 32 $ DEPTH $end
$var parameter 32 % WIDTH $end
$var reg 1 & clk $end
$var reg 8 ' d_in [7:0] $end
$var reg 1 ( rd_en $end
$var reg 1 ) rst_n $end
$var reg 1 * wr_en $end
$var integer 32 + idx [31:0] $end
$scope module dut $end
$var wire 1 & clk $end
$var wire 8 , din_i [7:0] $end
$var wire 1 ( rd_en_i $end
$var wire 1 ) rst_n $end
$var wire 1 * wr_en_i $end
$var wire 1 ! full_o $end
$var wire 1 " empty_o $end
$var parameter 32 - DEPTH $end
$var parameter 32 . WIDTH $end
$var parameter 32 / nbit $end
$var parameter 32 0 ncount $end
$var reg 4 1 count_d [3:0] $end
$var reg 4 2 count_q [3:0] $end
$var reg 8 3 dout_o [7:0] $end
$var reg 3 4 rdptr_d [2:0] $end
$var reg 3 5 rdptr_q [2:0] $end
$var reg 3 6 wrptr_d [2:0] $end
$var reg 3 7 wrptr_q [2:0] $end
$upscope $end
$upscope $end
$scope module tb_fifo $end
$scope module dut $end
$var reg 8 8 \mem[0] [7:0] $end
$upscope $end
$upscope $end
$scope module tb_fifo $end
$scope module dut $end
$var reg 8 9 \mem[1] [7:0] $end
$upscope $end
$upscope $end
$scope module tb_fifo $end
$scope module dut $end
$var reg 8 : \mem[2] [7:0] $end
$upscope $end
$upscope $end
$scope module tb_fifo $end
$scope module dut $end
$var reg 8 ; \mem[3] [7:0] $end
$upscope $end
$upscope $end
$scope module tb_fifo $end
$scope module dut $end
$var reg 8 < \mem[4] [7:0] $end
$upscope $end
$upscope $end
$scope module tb_fifo $end
$scope module dut $end
$var reg 8 = \mem[5] [7:0] $end
$upscope $end
$upscope $end
$scope module tb_fifo $end
$scope module dut $end
$var reg 8 > \mem[6] [7:0] $end
$upscope $end
$upscope $end
$scope module tb_fifo $end
$scope module dut $end
$var reg 8 ? \mem[7] [7:0] $end
$upscope $end
$upscope $end
$enddefinitions $end
$comment Show the parameter values. $end
$dumpall
b11 0
b10 /
b1000 .
b1000 -
b1000 %
b1000 $
$end
#0
$dumpvars
bx ?
bx >
bx =
bx <
bx ;
bx :
bx 9
bx 8
b0 7
b0 6
b0 5
b0 4
b0 3
b0 2
b0 1
b0 ,
b1000 +
0*
0)
0(
b0 '
1&
b0 #
1"
0!
$end
#5000
0&
#10000
1&
#15000
0&
#20000
1&
1)
#25000
0&
#30000
b100100 8
0"
b1 2
b1 7
b10 1
b10 6
1&
b100100 '
b100100 ,
1*
#35000
0&
#40000
b11 1
b11 6
b10000001 9
b10 2
b10 7
1&
b10000001 '
b10000001 ,
#45000
0&
#50000
b100 1
b100 6
b1001 :
b11 2
b11 7
1&
b1001 '
b1001 ,
#55000
0&
#60000
b101 1
b101 6
b1100011 ;
b100 2
b100 7
1&
b1100011 '
b1100011 ,
#65000
0&
#70000
b110 1
b110 6
b1101 <
b101 2
b101 7
1&
b1101 '
b1101 ,
#75000
0&
#80000
b111 1
b111 6
b10001101 =
b110 2
b110 7
1&
b10001101 '
b10001101 ,
#85000
0&
#90000
b1000 1
b0 6
b1100101 >
b111 2
b111 7
1&
b1100101 '
b1100101 ,
#95000
0&
#100000
b10010 ?
1!
b1000 2
b0 7
1&
b10010 '
b10010 ,
#105000
0&
#110000
1&
0*
#115000
0&
#120000
1&
#125000
0&
#130000
b100100 #
b100100 3
0!
b111 2
b1 5
b110 1
b10 4
1&
1(
#135000
0&
#140000
b101 1
b11 4
b10000001 #
b10000001 3
b110 2
b10 5
1&
#145000
0&
#150000
b100 1
b100 4
b1001 #
b1001 3
b101 2
b11 5
1&
#155000
0&
#160000
b11 1
b101 4
b1100011 #
b1100011 3
b100 2
b100 5
1&
#165000
0&
#170000
b10 1
b110 4
b1101 #
b1101 3
b11 2
b101 5
1&
#175000
0&
#180000
b1 1
b111 4
b10001101 #
b10001101 3
b10 2
b110 5
1&
#185000
0&
#190000
b0 1
b0 4
b1100101 #
b1100101 3
b1 2
b111 5
1&
#195000
0&
#200000
b10010 #
b10010 3
1"
b0 2
b0 5
1&
#205000
0&
#210000
b0 #
b0 3
1&
#215000
0&
#220000
1&
#225000
0&
#230000
1&
#235000
0&
#240000
1&
0(
#245000
0&
#250000
1&
#255000
0&
#260000
b10101010 #
b10101010 3
1&
b10101010 '
b10101010 ,
1*
1(
#265000
0&
#270000
b10111011 #
b10111011 3
1&
b10111011 '
b10111011 ,
#275000
0&
#280000
b11001100 #
b11001100 3
1&
b11001100 '
b11001100 ,
#285000
0&
#290000
b0 #
b0 3
1&
0*
#295000
0&
#300000
1&
0(
